nvfuser-0.0.9.dev20230508.dist-info/RECORD
nvfuser-0.0.9.dev20230508.dist-info/WHEEL
nvfuser-0.0.9.dev20230508.dist-info/METADATA
nvfuser-0.0.9.dev20230508.dist-info/top_level.txt
nvfuser-0.0.9.dev20230508.dist-info/LICENSE
nvfuser-0.0.9.dev20230508.dist-info/entry_points.txt
nvfuser_python_utils/patch_nvfuser.py
nvfuser_python_utils/__init__.py
nvfuser/pytorch_utils.py
nvfuser/version.py
nvfuser/nvfuser_version.py
nvfuser/_C.cpython-310-x86_64-linux-gnu.so
nvfuser/utils.py
nvfuser/__init__.py
nvfuser/include/nvfuser/mutator.h
nvfuser/include/nvfuser/non_divisible_split.h
nvfuser/include/nvfuser/ir_all_nodes.h
nvfuser/include/nvfuser/lower_instrument.h
nvfuser/include/nvfuser/lower_warp_reduce.h
nvfuser/include/nvfuser/lower_sync_information.h
nvfuser/include/nvfuser/grouped_reduction.h
nvfuser/include/nvfuser/lower_predicate_elimination.h
nvfuser/include/nvfuser/parallel_type_bitmap.h
nvfuser/include/nvfuser/register_interface.h
nvfuser/include/nvfuser/compute_at_map.h
nvfuser/include/nvfuser/lower_scalar_hoist.h
nvfuser/include/nvfuser/inlining.h
nvfuser/include/nvfuser/type_promotion.h
nvfuser/include/nvfuser/ir_builder_passkey.h
nvfuser/include/nvfuser/fusion_segmenter.h
nvfuser/include/nvfuser/manager.h
nvfuser/include/nvfuser/lower_predicate.h
nvfuser/include/nvfuser/dispatch.h
nvfuser/include/nvfuser/expr_simplifier.h
nvfuser/include/nvfuser/transform_view.h
nvfuser/include/nvfuser/ir_printer.h
nvfuser/include/nvfuser/parallel_dimension_map.h
nvfuser/include/nvfuser/lower_unroll.h
nvfuser/include/nvfuser/lower_index.h
nvfuser/include/nvfuser/type.h
nvfuser/include/nvfuser/lower_double_buffer.h
nvfuser/include/nvfuser/lower_vectorize_welford.h
nvfuser/include/nvfuser/lower_index_compute.h
nvfuser/include/nvfuser/partition.h
nvfuser/include/nvfuser/compute_at.h
nvfuser/include/nvfuser/dynamic_transform.h
nvfuser/include/nvfuser/fusion.h
nvfuser/include/nvfuser/ir_cloner.h
nvfuser/include/nvfuser/lower_shift.h
nvfuser/include/nvfuser/ir_interface_nodes.h
nvfuser/include/nvfuser/disjoint_set.h
nvfuser/include/nvfuser/ir_iostream.h
nvfuser/include/nvfuser/ir_builder.h
nvfuser/include/nvfuser/executor_utils.h
nvfuser/include/nvfuser/vectorization_info.h
