Metadata-Version: 2.1
Name: nvfuser
Version: 0.0.9.dev20230508
Summary: A Fusion Code Generator for NVIDIA GPUs (commonly known as 'nvFuser')
Home-page: https://github.com/NVIDIA/Fuser
License: BSD-3-Clause
License-File: LICENSE
Requires-Dist: nvidia-cuda-nvrtc-cu11
Requires-Dist: nvidia-nvtx-cu11
